README.md
pyproject.toml
setup.py
src/app/__init__.py
src/app/influx_query.py
src/app/solar_main.py
src/classes/__init__.py
src/classes/common_classes.py
src/classes/custom_exceptions.py
src/classes/influx_classes.py
src/classes/mqtt_classes.py
src/classes/query_classes.py
src/helpers/__init__.py
src/helpers/consts.py
src/helpers/py_functions.py
src/helpers/py_logger.py
src/solar_logger.egg-info/PKG-INFO
src/solar_logger.egg-info/SOURCES.txt
src/solar_logger.egg-info/dependency_links.txt
src/solar_logger.egg-info/requires.txt
src/solar_logger.egg-info/top_level.txt