Metadata-Version: 2.1
Name: solar-logger
Version: 1.2.0
Summary: MQTT to Influx DB converter for Outback solar controller
Home-page: https://github.com/WibblyGhost/solar_logger
Author: Zach Sanson
Author-email: zac@sanson.co.nz
Project-URL: Bug Tracker, https://github.com/WibblyGhost/solar_logger/issues
Classifier: Programming Language :: Python :: 3.10
Classifier: License :: OSI Approved :: MIT License
Classifier: Operating System :: OS Independent
Requires-Python: >=3.10
